pest_cli/__init__.py
pest_cli/_common/__init__.py
pest_cli/_common/components/component.py
pest_cli/_common/components/logo.py
pest_cli/_common/fprint/__init__.py
pest_cli/_common/fprint/at.py
pest_cli/_common/fprint/bg.py
pest_cli/_common/fprint/fg.py
pest_cli/_common/fprint/print_echo.py
pest_cli/_common/fprint/print_tree.py
pest_cli/_common/styles.py
pest_cli/_common/theme.py
pest_cli/app.py
pest_cli/cli/__init__.py
pest_cli/cli/commands/generate/__init__.py
pest_cli/cli/commands/generate/schematic.py
pest_cli/cli/commands/generate/subcommand.py
pest_cli/cli/help_formatter.py
pest_cli/engine/file/file.py
pest_cli/engine/file/types.py
pest_cli/engine/schema.py
pest_cli/schematics/__init__.py
pest_cli/schematics/application/schema.yaml
pest_cli/schematics/application/template/{{name}}/.gitignore.jinja
pest_cli/schematics/application/template/{{name}}/README.md.jinja
pest_cli/schematics/application/template/{{name}}/{{name}}/app_module.py.jinja
pest_cli/schematics/application/template/{{name}}/{{name}}/hello/greeter_service.py.jinja
pest_cli/schematics/application/template/{{name}}/{{name}}/hello/hello_controller.py.jinja
pest_cli/schematics/application/template/{{name}}/{{name}}/hello/module.py.jinja
pest_cli/schematics/application/template/{{name}}/{{name}}/main.py.jinja
pest_cli/schematics/application/template-[poetry]/{{name}}/poetry.toml.jinja
pest_cli/schematics/application/template-[poetry]/{{name}}/pyproject.toml.jinja
pest_cli-0.1.1.dist-info/METADATA
pest_cli-0.1.1.dist-info/WHEEL
pest_cli-0.1.1.dist-info/entry_points.txt
pest_cli-0.1.1.dist-info/RECORD
