Metadata-Version: 2.1
Name: pest-cli
Version: 0.1.1
Summary: 🐀 ⇝ cli tool for pest applications
Home-page: https://pest.lucode.ar
License: MIT
Keywords: pest,tool,cli,nestjs,nest,mvc,web,webapp,di,dependency injection,rodi,fastapi
Author: Lucas Colombo
Author-email: lucas@lucaslabs.tech
Requires-Python: >=3.8,<4.0
Classifier: Development Status :: 4 - Beta
Classifier: Environment :: Console
Classifier: Framework :: AsyncIO
Classifier: Framework :: FastAPI
Classifier: Framework :: Pydantic
Classifier: Framework :: Pydantic :: 1
Classifier: Intended Audience :: Developers
Classifier: Intended Audience :: Information Technology
Classifier: Intended Audience :: System Administrators
Classifier: License :: OSI Approved :: MIT License
Classifier: Operating System :: OS Independent
Classifier: Programming Language :: Python
Classifier: Programming Language :: Python :: 3
Classifier: Programming Language :: Python :: 3.8
Classifier: Programming Language :: Python :: 3.9
Classifier: Programming Language :: Python :: 3.10
Classifier: Programming Language :: Python :: 3.11
Classifier: Programming Language :: Python :: 3.12
Classifier: Topic :: Internet
Classifier: Topic :: Software Development
Classifier: Typing :: Typed
Requires-Dist: click (>=8.1.7,<9.0.0)
Requires-Dist: dataclass-wizard (>=0.22.3,<0.23.0)
Requires-Dist: inquirerpy (>=0.3.4,<0.4.0)
Requires-Dist: jinja2 (>=3.1.4,<4.0.0)
Requires-Dist: pygments (>=2.18.0,<3.0.0)
Requires-Dist: pyyaml (>=6.0.2,<7.0.0)
Requires-Dist: rich (>=13.7.1,<14.0.0)
Requires-Dist: tomli (>=2.0.1,<3.0.0)
Requires-Dist: typing-extensions (>=4.12.2,<5.0.0)
Project-URL: Documentation, https://pest.lucode.ar/docs
Project-URL: Repository, https://github.com/lucas-labs/pest-cli
